any2fixed-0.3.1.dist-info/DESCRIPTION.rst
any2fixed-0.3.1.dist-info/top_level.txt
any2fixed-0.3.1.dist-info/METADATA
any2fixed-0.3.1.dist-info/RECORD
any2fixed-0.3.1.dist-info/WHEEL
any2fixed-0.3.1.dist-info/metadata.json
any2fixed-0.3.1.dist-info/entry_points.txt
any2fixed/main.py
any2fixed/__init__.py
