Metadata-Version: 2.0
Name: any2fixed
Version: 0.3.1
Summary: A tool to generate fixed length files from a list of python instances
Home-page: UNKNOWN
Author: Florent Aide
Author-email: florent.aide@gmail.com
License: BSD License
Keywords: fixed length python
Platform: UNKNOWN
Classifier: Development Status :: 4 - Beta
Classifier: Intended Audience :: Developers
Classifier: License :: OSI Approved :: BSD License
Classifier: Operating System :: OS Independent
Classifier: Programming Language :: Python
Classifier: Topic :: Software Development :: Libraries :: Python Modules
Classifier: Topic :: Text Processing :: General
Requires-Dist: pyjon.utils
Requires-Dist: six
Requires-Dist: any2
